<?xml version="1.0" encoding="utf-8"?>
<LanguageData>

  <!-- Warmongering Gladiator Gavel -->

  <WoWM_Draenei_Gavel.label>好战角斗士的木槌</WoWM_Draenei_Gavel.label>
  <WoWM_Draenei_Gavel.description>好战角斗士的木槌</WoWM_Draenei_Gavel.description>
  <WoWM_Draenei_Gavel.tools.0.label>槌头</WoWM_Draenei_Gavel.tools.0.label>


  <!-- Anchorite Mace -->

  <WoWM_Draenei_Mace.label>埃索隆钉锤</WoWM_Draenei_Mace.label>
  <WoWM_Draenei_Mace.description>埃索隆钉锤</WoWM_Draenei_Mace.description>
  <WoWM_Draenei_Mace.tools.0.label>锤头</WoWM_Draenei_Mace.tools.0.label>


  <!-- Draenic Ribsmasher -->

  <WoWM_Draenei_Hammer.label>draenic hammer</WoWM_Draenei_Hammer.label>
  <WoWM_Draenei_Hammer.description>Draenic hammer</WoWM_Draenei_Hammer.description>
  <WoWM_Draenei_Hammer.tools.0.label>edge</WoWM_Draenei_Hammer.tools.0.label>


  <!-- Claymore of the Prophet -->

  <WoWM_Draenei_Claymore.label>先知的双刃刀</WoWM_Draenei_Claymore.label>
  <WoWM_Draenei_Claymore.description>先知的双刃刀</WoWM_Draenei_Claymore.description>
  <WoWM_Draenei_Claymore.tools.0.label>刀刃</WoWM_Draenei_Claymore.tools.0.label>


  <!-- Hammer of the Naaru -->

  <WoWM_Draenei__GreatHammer.label>纳鲁之锤</WoWM_Draenei__GreatHammer.label>
  <WoWM_Draenei__GreatHammer.description>纳鲁之锤</WoWM_Draenei__GreatHammer.description>
  <WoWM_Draenei__GreatHammer.tools.0.label>锤头</WoWM_Draenei__GreatHammer.tools.0.label>


</LanguageData>